anasfv/__init__.py
anasfv/completeness.py
anasfv/download_asfv_genome.py
anasfv/find_near_ref.py
anasfv/get_cds_alignments.py
anasfv/logger.py
anasfv/make_tree.py
anasfv/mapping_assembly.py
anasfv/polish_asfv.py
anasfv/readme.md
anasfv/recombination_plot.py
anasfv/recombination_test.py
anasfv/utils.py
anasfv/consensus_ffn/typeII_consensus.ffn
anasfv/consensus_ffn/typeII_consensus.ndb
anasfv/consensus_ffn/typeII_consensus.nhr
anasfv/consensus_ffn/typeII_consensus.nin
anasfv/consensus_ffn/typeII_consensus.not
anasfv/consensus_ffn/typeII_consensus.nsq
anasfv/consensus_ffn/typeII_consensus.ntf
anasfv/consensus_ffn/typeII_consensus.nto
anasfv/consensus_ffn/typeIImore_consensus.ffn
anasfv/consensus_ffn/typeIImore_consensus.ndb
anasfv/consensus_ffn/typeIImore_consensus.nhr
anasfv/consensus_ffn/typeIImore_consensus.nin
anasfv/consensus_ffn/typeIImore_consensus.not
anasfv/consensus_ffn/typeIImore_consensus.nsq
anasfv/consensus_ffn/typeIImore_consensus.ntf
anasfv/consensus_ffn/typeIImore_consensus.nto
anasfv/consensus_ffn/typeI_consensus.ffn
anasfv/consensus_ffn/typeI_consensus.ndb
anasfv/consensus_ffn/typeI_consensus.nhr
anasfv/consensus_ffn/typeI_consensus.nin
anasfv/consensus_ffn/typeI_consensus.not
anasfv/consensus_ffn/typeI_consensus.nsq
anasfv/consensus_ffn/typeI_consensus.ntf
anasfv/consensus_ffn/typeI_consensus.nto
anasfv/consensus_ffn/typeImore_consensus.ffn
anasfv/consensus_ffn/typeImore_consensus.ndb
anasfv/consensus_ffn/typeImore_consensus.nhr
anasfv/consensus_ffn/typeImore_consensus.nin
anasfv/consensus_ffn/typeImore_consensus.not
anasfv/consensus_ffn/typeImore_consensus.nsq
anasfv/consensus_ffn/typeImore_consensus.ntf
anasfv/consensus_ffn/typeImore_consensus.nto
anasfv/ref_cds/asfv_cds.fa
anasfv-0.0.12.data/scripts/completeness.py
anasfv-0.0.12.data/scripts/download_asfv_genome.py
anasfv-0.0.12.data/scripts/find_near_ref.py
anasfv-0.0.12.data/scripts/get_cds_alignments.py
anasfv-0.0.12.data/scripts/make_tree.py
anasfv-0.0.12.data/scripts/mapping_assembly.py
anasfv-0.0.12.dist-info/LICENSE
anasfv-0.0.12.dist-info/METADATA
anasfv-0.0.12.dist-info/WHEEL
anasfv-0.0.12.dist-info/top_level.txt
anasfv-0.0.12.dist-info/RECORD
