Metadata-Version: 2.1
Name: anasfv
Version: 0.0.12
Summary: The anasfv project focuses on analyzing nanopore-sequenced data of PCR-amplified African Swine Fever Virus (ASFV).
Home-page: https://github.com/lrslab/anasfv
Author: like
Author-email: taxoroger@gmail.com
License: MIT
License-File: LICENSE
Requires-Dist: biopython (>=1.8.1)
Requires-Dist: pandas (==2.0.3)
Requires-Dist: pyyaml (>=5.3.1)
Requires-Dist: pycirclize (>=1.6.0)
